LICENSE
README.md
setup.py
example_pkg/__init__.py
example_pkg/typing_extensions.py
example_pkg/_yaml/__init__.py
example_pkg/certifi/__init__.py
example_pkg/certifi/__main__.py
example_pkg/certifi/core.py
example_pkg/certifi/py.typed
example_pkg/charset_normalizer/__init__.py
example_pkg/charset_normalizer/__main__.py
example_pkg/charset_normalizer/api.py
example_pkg/charset_normalizer/cd.py
example_pkg/charset_normalizer/constant.py
example_pkg/charset_normalizer/legacy.py
example_pkg/charset_normalizer/md.py
example_pkg/charset_normalizer/models.py
example_pkg/charset_normalizer/py.typed
example_pkg/charset_normalizer/utils.py
example_pkg/charset_normalizer/version.py
example_pkg/charset_normalizer/cli/__init__.py
example_pkg/charset_normalizer/cli/__main__.py
example_pkg/filelock/__init__.py
example_pkg/filelock/_api.py
example_pkg/filelock/_error.py
example_pkg/filelock/_soft.py
example_pkg/filelock/_unix.py
example_pkg/filelock/_util.py
example_pkg/filelock/_windows.py
example_pkg/filelock/asyncio.py
example_pkg/filelock/py.typed
example_pkg/filelock/version.py
example_pkg/fsspec/__init__.py
example_pkg/fsspec/_version.py
example_pkg/fsspec/archive.py
example_pkg/fsspec/asyn.py
example_pkg/fsspec/caching.py
example_pkg/fsspec/callbacks.py
example_pkg/fsspec/compression.py
example_pkg/fsspec/config.py
example_pkg/fsspec/conftest.py
example_pkg/fsspec/core.py
example_pkg/fsspec/dircache.py
example_pkg/fsspec/exceptions.py
example_pkg/fsspec/fuse.py
example_pkg/fsspec/generic.py
example_pkg/fsspec/gui.py
example_pkg/fsspec/json.py
example_pkg/fsspec/mapping.py
example_pkg/fsspec/parquet.py
example_pkg/fsspec/registry.py
example_pkg/fsspec/spec.py
example_pkg/fsspec/transaction.py
example_pkg/fsspec/utils.py
example_pkg/fsspec/implementations/__init__.py
example_pkg/fsspec/implementations/arrow.py
example_pkg/fsspec/implementations/asyn_wrapper.py
example_pkg/fsspec/implementations/cache_mapper.py
example_pkg/fsspec/implementations/cache_metadata.py
xjhtrans.egg-info/PKG-INFO
xjhtrans.egg-info/SOURCES.txt
xjhtrans.egg-info/dependency_links.txt
xjhtrans.egg-info/top_level.txt