Metadata-Version: 2.2
Name: xjhtrans
Version: 0.0.1
Summary: A small example package
Home-page: https://github.com/pypa/sampleproject
Author: xujiahao
Author-email: xujiahao056@gmail.com
Classifier: Programming Language :: Python :: 3
Classifier: License :: OSI Approved :: MIT License
Classifier: Operating System :: OS Independent
License-File: LICENSE
Dynamic: author
Dynamic: author-email
Dynamic: classifier
Dynamic: description
Dynamic: description-content-type
Dynamic: home-page
Dynamic: summary
